src/__init__.py
repo_reader-0.0.1.dist-info/METADATA
repo_reader-0.0.1.dist-info/WHEEL
repo_reader-0.0.1.dist-info/top_level.txt
repo_reader-0.0.1.dist-info/RECORD
